Workbook

Sheet Dashboard
A1: DASHBOARD
A3: Sistema de Gestión de Andy Silverio
A5: TOTAL VENTAS ($) | E5: TOTAL COMPRAS ($) | I5: GANANCIA NETA ($) | M5: UNIDADES VENDIDAS
A6: =IFERROR(SUM(Ventas!F4:F500),0) -> 65442 | E6: =IFERROR(SUM(Compras!F4:F500),0) -> 185216 | I6: =IFERROR(SUM(Rentabilidad!I4:I103),0) -> 14651 | M6: =IFERROR(SUM(Ventas!D4:D500),0) -> 254
A10: PRODUCTOS EN CATÁLOGO | E10: MARGEN PROMEDIO | I10: PRODUCTO MÁS VENDIDO | M10: ITEMS EN STOCK CRÍTICO
A11: =COUNTA(Productos!A4:A200) -> 101 | E11: =IFERROR(AVERAGE(Rentabilidad!J4:J103),0) -> 0.52107878 | I11: =IFERROR(INDEX(Productos!B4:B103,MATCH(MAX(Rentabilidad!F4:F103),Rentabilidad!F4:F103,0)),"—") -> Mouse Office Silent | M11: =COUNTIF(Inventario!G4:G103,"Crítico") -> 3
A16: TOP 10 PRODUCTOS | H16: RESUMEN POR CATEGORÍA
A17: ID | B17: Producto | C17: Uds. Vendidas | D17: Ingresos ($) | H17: Categoría | I17: Prod. | J17: Uds. Vendidas | K17: Ingresos ($) | L17: Ganancia ($)
A18: =IFERROR(INDEX(Rentabilidad!$A$4:$A$103,MATCH(LARGE(Rentabilidad!$F$4:$F$103,1),Rentabilidad!$F$4:$F$103,0)),"") -> P008 | B18: =IFERROR(INDEX(Rentabilidad!$B$4:$B$103,MATCH(LARGE(Rentabilidad!$F$4:$F$103,1),Rentabilidad!$F$4:$F$103,0)),"") -> Mouse Office Silent | C18: =IFERROR(LARGE(Rentabilidad!$F$4:$F$103,1),0) -> 7 | D18: =IFERROR(INDEX(Rentabilidad!$G$4:$G$103,MATCH(LARGE(Rentabilidad!$F$4:$F$103,1),Rentabilidad!$F$4:$F$103,0)),0) -> 210 | H18: Computadoras | I18: =COUNTIF(Productos!$C:$C,H18) -> 5 | J18: =SUMIF(Rentabilidad!$C$4:$C$103,H18,Rentabilidad!$F$4:$F$103) -> 12 | K18: =SUMIF(Rentabilidad!$C$4:$C$103,H18,Rentabilidad!$G$4:$G$103) -> 10690 | L18: =SUMIF(Rentabilidad!$C$4:$C$103,H18,Rentabilidad!$I$4:$I$103) -> 3550
A19: =IFERROR(INDEX(Rentabilidad!$A$4:$A$103,MATCH(LARGE(Rentabilidad!$F$4:$F$103,2),Rentabilidad!$F$4:$F$103,0)),"") -> P006 | B19: =IFERROR(INDEX(Rentabilidad!$B$4:$B$103,MATCH(LARGE(Rentabilidad!$F$4:$F$103,2),Rentabilidad!$F$4:$F$103,0)),"") -> Mouse Gamer RGB | C19: =IFERROR(LARGE(Rentabilidad!$F$4:$F$103,2),0) -> 6 | D19: =IFERROR(INDEX(Rentabilidad!$G$4:$G$103,MATCH(LARGE(Rentabilidad!$F$4:$F$103,2),Rentabilidad!$F$4:$F$103,0)),0) -> 252 | H19: Accesorios | I19: =COUNTIF(Productos!$C:$C,H19) -> 15 | J19: =SUMIF(Rentabilidad!$C$4:$C$103,H19,Rentabilidad!$F$4:$F$103) -> 57 | K19: =SUMIF(Rentabilidad!$C$4:$C$103,H19,Rentabilidad!$G$4:$G$103) -> 2665 | L19: =SUMIF(Rentabilidad!$C$4:$C$103,H19,Rentabilidad!$I$4:$I$103) -> 1506
A20: =IFERROR(INDEX(Rentabilidad!$A$4:$A$103,MATCH(LARGE(Rentabilidad!$F$4:$F$103,3),Rentabilidad!$F$4:$F$103,0)),"") -> P006 | B20: =IFERROR(INDEX(Rentabilidad!$B$4:$B$103,MATCH(LARGE(Rentabilidad!$F$4:$F$103,3),Rentabilidad!$F$4:$F$103,0)),"") -> Mouse Gamer RGB | C20: =IFERROR(LARGE(Rentabilidad!$F$4:$F$103,3),0) -> 6 | D20: =IFERROR(INDEX(Rentabilidad!$G$4:$G$103,MATCH(LARGE(Rentabilidad!$F$4:$F$103,3),Rentabilidad!$F$4:$F$103,0)),0) -> 252 | H20: Monitores | I20: =COUNTIF(Productos!$C:$C,H20) -> 5 | J20: =SUMIF(Rentabilidad!$C$4:$C$103,H20,Rentabilidad!$F$4:$F$103) -> 6 | K20: =SUMIF(Rentabilidad!$C$4:$C$103,H20,Rentabilidad!$G$4:$G$103) -> 1730 | L20: =SUMIF(Rentabilidad!$C$4:$C$103,H20,Rentabilidad!$I$4:$I$103) -> 675
A21: =IFERROR(INDEX(Rentabilidad!$A$4:$A$103,MATCH(LARGE(Rentabilidad!$F$4:$F$103,4),Rentabilidad!$F$4:$F$103,0)),"") -> P006 | B21: =IFERROR(INDEX(Rentabilidad!$B$4:$B$103,MATCH(LARGE(Rentabilidad!$F$4:$F$103,4),Rentabilidad!$F$4:$F$103,0)),"") -> Mouse Gamer RGB | C21: =IFERROR(LARGE(Rentabilidad!$F$4:$F$103,4),0) -> 6 | D21: =IFERROR(INDEX(Rentabilidad!$G$4:$G$103,MATCH(LARGE(Rentabilidad!$F$4:$F$103,4),Rentabilidad!$F$4:$F$103,0)),0) -> 252 | H21: Periféricos | I21: =COUNTIF(Productos!$C:$C,H21) -> 5 | J21: =SUMIF(Rentabilidad!$C$4:$C$103,H21,Rentabilidad!$F$4:$F$103) -> 16 | K21: =SUMIF(Rentabilidad!$C$4:$C$103,H21,Rentabilidad!$G$4:$G$103) -> 1151 | L21: =SUMIF(Rentabilidad!$C$4:$C$103,H21,Rentabilidad!$I$4:$I$103) -> 597
A22: =IFERROR(INDEX(Rentabilidad!$A$4:$A$103,MATCH(LARGE(Rentabilidad!$F$4:$F$103,5),Rentabilidad!$F$4:$F$103,0)),"") -> P007 | B22: =IFERROR(INDEX(Rentabilidad!$B$4:$B$103,MATCH(LARGE(Rentabilidad!$F$4:$F$103,5),Rentabilidad!$F$4:$F$103,0)),"") -> Mouse Wireless Pro | C22: =IFERROR(LARGE(Rentabilidad!$F$4:$F$103,5),0) -> 5 | D22: =IFERROR(INDEX(Rentabilidad!$G$4:$G$103,MATCH(LARGE(Rentabilidad!$F$4:$F$103,5),Rentabilidad!$F$4:$F$103,0)),0) -> 240 | H22: Almacenamiento | I22: =COUNTIF(Productos!$C:$C,H22) -> 10 | J22: =SUMIF(Rentabilidad!$C$4:$C$103,H22,Rentabilidad!$F$4:$F$103) -> 27 | K22: =SUMIF(Rentabilidad!$C$4:$C$103,H22,Rentabilidad!$G$4:$G$103) -> 3460 | L22: =SUMIF(Rentabilidad!$C$4:$C$103,H22,Rentabilidad!$I$4:$I$103) -> 1633
A23: =IFERROR(INDEX(Rentabilidad!$A$4:$A$103,MATCH(LARGE(Rentabilidad!$F$4:$F$103,6),Rentabilidad!$F$4:$F$103,0)),"") -> P007 | B23: =IFERROR(INDEX(Rentabilidad!$B$4:$B$103,MATCH(LARGE(Rentabilidad!$F$4:$F$103,6),Rentabilidad!$F$4:$F$103,0)),"") -> Mouse Wireless Pro | C23: =IFERROR(LARGE(Rentabilidad!$F$4:$F$103,6),0) -> 5 | D23: =IFERROR(INDEX(Rentabilidad!$G$4:$G$103,MATCH(LARGE(Rentabilidad!$F$4:$F$103,6),Rentabilidad!$F$4:$F$103,0)),0) -> 240 | H23: Audio | I23: =COUNTIF(Productos!$C:$C,H23) -> 5 | J23: =SUMIF(Rentabilidad!$C$4:$C$103,H23,Rentabilidad!$F$4:$F$103) -> 16 | K23: =SUMIF(Rentabilidad!$C$4:$C$103,H23,Rentabilidad!$G$4:$G$103) -> 1230 | L23: =SUMIF(Rentabilidad!$C$4:$C$103,H23,Rentabilidad!$I$4:$I$103) -> 651
A24: =IFERROR(INDEX(Rentabilidad!$A$4:$A$103,MATCH(LARGE(Rentabilidad!$F$4:$F$103,7),Rentabilidad!$F$4:$F$103,0)),"") -> P007 | B24: =IFERROR(INDEX(Rentabilidad!$B$4:$B$103,MATCH(LARGE(Rentabilidad!$F$4:$F$103,7),Rentabilidad!$F$4:$F$103,0)),"") -> Mouse Wireless Pro | C24: =IFERROR(LARGE(Rentabilidad!$F$4:$F$103,7),0) -> 5 | D24: =IFERROR(INDEX(Rentabilidad!$G$4:$G$103,MATCH(LARGE(Rentabilidad!$F$4:$F$103,7),Rentabilidad!$F$4:$F$103,0)),0) -> 240 | H24: Redes | I24: =COUNTIF(Productos!$C:$C,H24) -> 5 | J24: =SUMIF(Rentabilidad!$C$4:$C$103,H24,Rentabilidad!$F$4:$F$103) -> 9 | K24: =SUMIF(Rentabilidad!$C$4:$C$103,H24,Rentabilidad!$G$4:$G$103) -> 785 | L24: =SUMIF(Rentabilidad!$C$4:$C$103,H24,Rentabilidad!$I$4:$I$103) -> 431
A25: =IFERROR(INDEX(Rentabilidad!$A$4:$A$103,MATCH(LARGE(Rentabilidad!$F$4:$F$103,8),Rentabilidad!$F$4:$F$103,0)),"") -> P007 | B25: =IFERROR(INDEX(Rentabilidad!$B$4:$B$103,MATCH(LARGE(Rentabilidad!$F$4:$F$103,8),Rentabilidad!$F$4:$F$103,0)),"") -> Mouse Wireless Pro | C25: =IFERROR(LARGE(Rentabilidad!$F$4:$F$103,8),0) -> 5 | D25: =IFERROR(INDEX(Rentabilidad!$G$4:$G$103,MATCH(LARGE(Rentabilidad!$F$4:$F$103,8),Rentabilidad!$F$4:$F$103,0)),0) -> 240 | H25: Cables | I25: =COUNTIF(Productos!$C:$C,H25) -> 5 | J25: =SUMIF(Rentabilidad!$C$4:$C$103,H25,Rentabilidad!$F$4:$F$103) -> 26 | K25: =SUMIF(Rentabilidad!$C$4:$C$103,H25,Rentabilidad!$G$4:$G$103) -> 412 | L25: =SUMIF(Rentabilidad!$C$4:$C$103,H25,Rentabilidad!$I$4:$I$103) -> 291
A26: =IFERROR(INDEX(Rentabilidad!$A$4:$A$103,MATCH(LARGE(Rentabilidad!$F$4:$F$103,9),Rentabilidad!$F$4:$F$103,0)),"") -> P007 | B26: =IFERROR(INDEX(Rentabilidad!$B$4:$B$103,MATCH(LARGE(Rentabilidad!$F$4:$F$103,9),Rentabilidad!$F$4:$F$103,0)),"") -> Mouse Wireless Pro | C26: =IFERROR(LARGE(Rentabilidad!$F$4:$F$103,9),0) -> 5 | D26: =IFERROR(INDEX(Rentabilidad!$G$4:$G$103,MATCH(LARGE(Rentabilidad!$F$4:$F$103,9),Rentabilidad!$F$4:$F$103,0)),0) -> 240 | H26: Tablets | I26: =COUNTIF(Productos!$C:$C,H26) -> 5 | J26: =SUMIF(Rentabilidad!$C$4:$C$103,H26,Rentabilidad!$F$4:$F$103) -> 7 | K26: =SUMIF(Rentabilidad!$C$4:$C$103,H26,Rentabilidad!$G$4:$G$103) -> 1680 | L26: =SUMIF(Rentabilidad!$C$4:$C$103,H26,Rentabilidad!$I$4:$I$103) -> 650
A27: =IFERROR(INDEX(Rentabilidad!$A$4:$A$103,MATCH(LARGE(Rentabilidad!$F$4:$F$103,10),Rentabilidad!$F$4:$F$103,0)),"") -> P007 | B27: =IFERROR(INDEX(Rentabilidad!$B$4:$B$103,MATCH(LARGE(Rentabilidad!$F$4:$F$103,10),Rentabilidad!$F$4:$F$103,0)),"") -> Mouse Wireless Pro | C27: =IFERROR(LARGE(Rentabilidad!$F$4:$F$103,10),0) -> 5 | D27: =IFERROR(INDEX(Rentabilidad!$G$4:$G$103,MATCH(LARGE(Rentabilidad!$F$4:$F$103,10),Rentabilidad!$F$4:$F$103,0)),0) -> 240 | H27: Impresoras | I27: =COUNTIF(Productos!$C:$C,H27) -> 5 | J27: =SUMIF(Rentabilidad!$C$4:$C$103,H27,Rentabilidad!$F$4:$F$103) -> 8 | K27: =SUMIF(Rentabilidad!$C$4:$C$103,H27,Rentabilidad!$G$4:$G$103) -> 1380 | L27: =SUMIF(Rentabilidad!$C$4:$C$103,H27,Rentabilidad!$I$4:$I$103) -> 700
A30: RESUMEN FINANCIERO
A31: Total Ventas ($) | E31: Total Compras ($) | I31: Ganancia Bruta ($) | M31: Margen Neto (%)
A32: =IFERROR(SUM(Ventas!F4:F500),0) -> 65442 | E32: =IFERROR(SUM(Compras!F4:F500),0) -> 185216 | I32: =IFERROR(SUM(Rentabilidad!I4:I103),0) -> 14651 | M32: =IFERROR(SUM(Rentabilidad!I4:I103)/SUM(Ventas!F4:F500),0) -> 0.22387763

Sheet Formulario
A1: FORMULARIO DE INGRESO DE DATOS
A3: Sistema de Gestión de Andy Silverio
A5: NUEVA VENTA | I5: NUEVA COMPRA
A6: Fecha: | I6: Fecha:
A7: ID Producto: | I7: ID Producto:
A8: Nombre (auto): | B8: =IFERROR(VLOOKUP(B7,Productos!$A:$B,2,0),"— ingrese un ID Válido —") -> — ingrese un ID Válido — | I8: Nombre (auto): | J8: =IFERROR(VLOOKUP(J7,Productos!$A:$B,2,0),"— ingrese ID válido —") -> — ingrese ID válido —
A9: Cantidad: | I9: Cantidad:
A10: Precio Venta (auto): | B10: =IFERROR(VLOOKUP(B7,Productos!$A:$E,5,0),"—") -> — | I10: Costo Unit. (auto): | J10: =IFERROR(VLOOKUP(J7,Productos!$A:$D,4,0),"—") -> —
A11: TOTAL VENTA: | B11: =IFERROR(B9*B10,"") | I11: TOTAL COMPRA: | J11: =IFERROR(J9*J10,"")
A13: AGREGAR NUEVO PRODUCTO AL CATALOGO
A15: ID Producto:
A16: Nombre:
A17: Categoría:
A18: Costo Unitario ($):
A19: Precio de Venta ($):
A20: Margen calc.: | B20: =IFERROR((B19-B18)/B18,"")

Sheet Productos
A1: CATÁLOGO DE PRODUCTOS
A2: Sistema de Gestión de Andy Silverio
A3: ID Producto | B3: Nombre del Producto | C3: Categoría | D3: Costo Unitario ($) | E3: Precio de Venta ($) | F3: Margen (%)
A4: P001 | B4: Laptop X1 | C4: Computadoras | D4: 620 | E4: 920 | F4: =IFERROR((E4-D4)/D4,0) -> 0.48387097
A5: P002 | B5: Laptop AirLite | C5: Computadoras | D5: 540 | E5: 820 | F5: =IFERROR((E5-D5)/D5,0) -> 0.51851852
A6: P003 | B6: Laptop ProMax | C6: Computadoras | D6: 780 | E6: 1150 | F6: =IFERROR((E6-D6)/D6,0) -> 0.47435897
A7: P004 | B7: Mini Laptop Go | C7: Computadoras | D7: 410 | E7: 640 | F7: =IFERROR((E7-D7)/D7,0) -> 0.56097561
A8: P005 | B8: Laptop Studio | C8: Computadoras | D8: 890 | E8: 1290 | F8: =IFERROR((E8-D8)/D8,0) -> 0.4494382
A9: P006 | B9: Mouse Gamer RGB | C9: Accesorios | D9: 18 | E9: 42 | F9: =IFERROR((E9-D9)/D9,0) -> 1.3333333
A10: P007 | B10: Mouse Wireless Pro | C10: Accesorios | D10: 22 | E10: 48 | F10: =IFERROR((E10-D10)/D10,0) -> 1.1818182
A11: P008 | B11: Mouse Office Silent | C11: Accesorios | D11: 12 | E11: 30 | F11: =IFERROR((E11-D11)/D11,0) -> 1.5
A12: P009 | B12: Mouse UltraLight | C12: Accesorios | D12: 25 | E12: 55 | F12: =IFERROR((E12-D12)/D12,0) -> 1.2
A13: P010 | B13: Mouse Precision | C13: Accesorios | D13: 19 | E13: 40 | F13: =IFERROR((E13-D13)/D13,0) -> 1.1052632
A14: P011 | B14: Teclado Mecánico Red | C14: Accesorios | D14: 45 | E14: 95 | F14: =IFERROR((E14-D14)/D14,0) -> 1.1111111
A15: P012 | B15: Teclado Mecánico Blue | C15: Accesorios | D15: 48 | E15: 99 | F15: =IFERROR((E15-D15)/D15,0) -> 1.0625
... A103: P100 | B103: Procesador CoreX | C103: Componentes | D103: 210 | E103: 360 | F103: =IFERROR((E103-D103)/D103,0) -> 0.71428571
A104: TOTAL | D104: =AVERAGE(D4:D103) -> 96.91 | E104: =AVERAGE(E4:E103) -> 172.22 | F104: =AVERAGE(F4:F103) -> 1.1690654

Sheet Compras
A1: REGISTRO DE COMPRAS
A2: Sistema de Gestión de Andy Silverio
A3: Fecha | B3: ID Producto | C3: Nombre del Producto | D3: Cantidad | E3: Costo Unitario ($) | F3: Total Compra ($)
A4: 46023 | B4: P001 | C4: =IFERROR(VLOOKUP(B4,Productos!$A:$B,2,0),"") -> Laptop X1 | D4: 12 | E4: =IFERROR(VLOOKUP(B4,Productos!$A:$D,4,0),"") -> 620 | F4: =IFERROR(D4*E4,"") -> 7440
A5: 46024 | B5: P002 | C5: =IFERROR(VLOOKUP(B5,Productos!$A:$B,2,0),"") -> Laptop AirLite | D5: 8 | E5: =IFERROR(VLOOKUP(B5,Productos!$A:$D,4,0),"") -> 540 | F5: =IFERROR(D5*E5,"") -> 4320
A6: 46025 | B6: P003 | C6: =IFERROR(VLOOKUP(B6,Productos!$A:$B,2,0),"") -> Laptop ProMax | D6: 6 | E6: =IFERROR(VLOOKUP(B6,Productos!$A:$D,4,0),"") -> 780 | F6: =IFERROR(D6*E6,"") -> 4680
A7: 46026 | B7: P004 | C7: =IFERROR(VLOOKUP(B7,Productos!$A:$B,2,0),"") -> Mini Laptop Go | D7: 10 | E7: =IFERROR(VLOOKUP(B7,Productos!$A:$D,4,0),"") -> 410 | F7: =IFERROR(D7*E7,"") -> 4100
A8: 46027 | B8: P005 | C8: =IFERROR(VLOOKUP(B8,Productos!$A:$B,2,0),"") -> Laptop Studio | D8: 5 | E8: =IFERROR(VLOOKUP(B8,Productos!$A:$D,4,0),"") -> 890 | F8: =IFERROR(D8*E8,"") -> 4450
A9: 46028 | B9: P006 | C9: =IFERROR(VLOOKUP(B9,Productos!$A:$B,2,0),"") -> Mouse Gamer RGB | D9: 30 | E9: =IFERROR(VLOOKUP(B9,Productos!$A:$D,4,0),"") -> 18 | F9: =IFERROR(D9*E9,"") -> 540
A10: 46029 | B10: P007 | C10: =IFERROR(VLOOKUP(B10,Productos!$A:$B,2,0),"") -> Mouse Wireless Pro | D10: 25 | E10: =IFERROR(VLOOKUP(B10,Productos!$A:$D,4,0),"") -> 22 | F10: =IFERROR(D10*E10,"") -> 550
A11: 46030 | B11: P008 | C11: =IFERROR(VLOOKUP(B11,Productos!$A:$B,2,0),"") -> Mouse Office Silent | D11: 40 | E11: =IFERROR(VLOOKUP(B11,Productos!$A:$D,4,0),"") -> 12 | F11: =IFERROR(D11*E11,"") -> 480
A12: 46031 | B12: P009 | C12: =IFERROR(VLOOKUP(B12,Productos!$A:$B,2,0),"") -> Mouse UltraLight | D12: 18 | E12: =IFERROR(VLOOKUP(B12,Productos!$A:$D,4,0),"") -> 25 | F12: =IFERROR(D12*E12,"") -> 450
A13: 46032 | B13: P010 | C13: =IFERROR(VLOOKUP(B13,Productos!$A:$B,2,0),"") -> Mouse Precision | D13: 22 | E13: =IFERROR(VLOOKUP(B13,Productos!$A:$D,4,0),"") -> 19 | F13: =IFERROR(D13*E13,"") -> 418
A14: 46033 | B14: P011 | C14: =IFERROR(VLOOKUP(B14,Productos!$A:$B,2,0),"") -> Teclado Mecánico Red | D14: 14 | E14: =IFERROR(VLOOKUP(B14,Productos!$A:$D,4,0),"") -> 45 | F14: =IFERROR(D14*E14,"") -> 630
A15: 46034 | B15: P012 | C15: =IFERROR(VLOOKUP(B15,Productos!$A:$B,2,0),"") -> Teclado Mecánico Blue | D15: 16 | E15: =IFERROR(VLOOKUP(B15,Productos!$A:$D,4,0),"") -> 48 | F15: =IFERROR(D15*E15,"") -> 768
... A103: 46111 | B103: P100 | C103: =IFERROR(VLOOKUP(B103,Productos!$A:$B,2,0),"") -> Procesador CoreX | D103: 9 | E103: =IFERROR(VLOOKUP(B103,Productos!$A:$D,4,0),"") -> 210 | F103: =IFERROR(D103*E103,"") -> 1890
A104: TOTAL COMPRAS | F104: =SUM(F4:F103) -> 92608

Sheet Ventas
A1: REGISTRO DE VENTAS
A2: Sistema de Gestión de Andy Silverio
A3: Fecha | B3: ID Producto | C3: Nombre del Producto | D3: Cantidad | E3: Precio Venta ($) | F3: Total Venta ($)
A4: 46024 | B4: P001 | C4: =IFERROR(VLOOKUP(B4,Productos!$A:$B,2,0),"") -> Laptop X1 | D4: 3 | E4: =IFERROR(VLOOKUP(B4,Productos!$A:$E,5,0),"") -> 920 | F4: =IFERROR(D4*E4,"") -> 2760
A5: 46025 | B5: P002 | C5: =IFERROR(VLOOKUP(B5,Productos!$A:$B,2,0),"") -> Laptop AirLite | D5: 2 | E5: =IFERROR(VLOOKUP(B5,Productos!$A:$E,5,0),"") -> 820 | F5: =IFERROR(D5*E5,"") -> 1640
A6: 46026 | B6: P003 | C6: =IFERROR(VLOOKUP(B6,Productos!$A:$B,2,0),"") -> Laptop ProMax | D6: 1 | E6: =IFERROR(VLOOKUP(B6,Productos!$A:$E,5,0),"") -> 1150 | F6: =IFERROR(D6*E6,"") -> 1150
A7: 46027 | B7: P004 | C7: =IFERROR(VLOOKUP(B7,Productos!$A:$B,2,0),"") -> Mini Laptop Go | D7: 4 | E7: =IFERROR(VLOOKUP(B7,Productos!$A:$E,5,0),"") -> 640 | F7: =IFERROR(D7*E7,"") -> 2560
A8: 46028 | B8: P005 | C8: =IFERROR(VLOOKUP(B8,Productos!$A:$B,2,0),"") -> Laptop Studio | D8: 2 | E8: =IFERROR(VLOOKUP(B8,Productos!$A:$E,5,0),"") -> 1290 | F8: =IFERROR(D8*E8,"") -> 2580
A9: 46029 | B9: P006 | C9: =IFERROR(VLOOKUP(B9,Productos!$A:$B,2,0),"") -> Mouse Gamer RGB | D9: 6 | E9: =IFERROR(VLOOKUP(B9,Productos!$A:$E,5,0),"") -> 42 | F9: =IFERROR(D9*E9,"") -> 252
A10: 46030 | B10: P007 | C10: =IFERROR(VLOOKUP(B10,Productos!$A:$B,2,0),"") -> Mouse Wireless Pro | D10: 5 | E10: =IFERROR(VLOOKUP(B10,Productos!$A:$E,5,0),"") -> 48 | F10: =IFERROR(D10*E10,"") -> 240
A11: 46031 | B11: P008 | C11: =IFERROR(VLOOKUP(B11,Productos!$A:$B,2,0),"") -> Mouse Office Silent | D11: 7 | E11: =IFERROR(VLOOKUP(B11,Productos!$A:$E,5,0),"") -> 30 | F11: =IFERROR(D11*E11,"") -> 210
A12: 46032 | B12: P009 | C12: =IFERROR(VLOOKUP(B12,Productos!$A:$B,2,0),"") -> Mouse UltraLight | D12: 3 | E12: =IFERROR(VLOOKUP(B12,Productos!$A:$E,5,0),"") -> 55 | F12: =IFERROR(D12*E12,"") -> 165
A13: 46033 | B13: P010 | C13: =IFERROR(VLOOKUP(B13,Productos!$A:$B,2,0),"") -> Mouse Precision | D13: 4 | E13: =IFERROR(VLOOKUP(B13,Productos!$A:$E,5,0),"") -> 40 | F13: =IFERROR(D13*E13,"") -> 160
A14: 46034 | B14: P011 | C14: =IFERROR(VLOOKUP(B14,Productos!$A:$B,2,0),"") -> Teclado Mecánico Red | D14: 2 | E14: =IFERROR(VLOOKUP(B14,Productos!$A:$E,5,0),"") -> 95 | F14: =IFERROR(D14*E14,"") -> 190
A15: 46035 | B15: P012 | C15: =IFERROR(VLOOKUP(B15,Productos!$A:$B,2,0),"") -> Teclado Mecánico Blue | D15: 2 | E15: =IFERROR(VLOOKUP(B15,Productos!$A:$E,5,0),"") -> 99 | F15: =IFERROR(D15*E15,"") -> 198
... A103: 46111 | B103: P100 | C103: =IFERROR(VLOOKUP(B103,Productos!$A:$B,2,0),"") -> Procesador CoreX | D103: 1 | E103: =IFERROR(VLOOKUP(B103,Productos!$A:$E,5,0),"") -> 360 | F103: =IFERROR(D103*E103,"") -> 360
A104: TOTAL VENTAS | F104: =SUM(F4:F103) -> 32721

Sheet Inventario
A1: CONTROL DE INVENTARIO
A2: Sistema de Gestión de Andy Silverio
A3: ID Producto | B3: Nombre del Producto | C3: Categoría | D3: Total Comprado | E3: Total Vendido | F3: Stock Actual | G3: Estado
A4: P001 | B4: Laptop X1 | C4: Computadoras | D4: =SUMIF(Compras!$B:$B,A4,Compras!$D:$D) -> 12 | E4: =SUMIF(Ventas!$B:$B,A4,Ventas!$D:$D) -> 3 | F4: =D4-E4 -> 9 | G4: =IF(F4<=0,"Sin Stock",IF(F4<5,"Crítico",IF(F4<10,"Stock Bajo","OK"))) -> Stock Bajo
A5: P002 | B5: Laptop AirLite | C5: Computadoras | D5: =SUMIF(Compras!$B:$B,A5,Compras!$D:$D) -> 8 | E5: =SUMIF(Ventas!$B:$B,A5,Ventas!$D:$D) -> 2 | F5: =D5-E5 -> 6 | G5: =IF(F5<=0,"Sin Stock",IF(F5<5,"Crítico",IF(F5<10,"Stock Bajo","OK"))) -> Stock Bajo
A6: P003 | B6: Laptop ProMax | C6: Computadoras | D6: =SUMIF(Compras!$B:$B,A6,Compras!$D:$D) -> 6 | E6: =SUMIF(Ventas!$B:$B,A6,Ventas!$D:$D) -> 1 | F6: =D6-E6 -> 5 | G6: =IF(F6<=0,"Sin Stock",IF(F6<5,"Crítico",IF(F6<10,"Stock Bajo","OK"))) -> Stock Bajo
A7: P004 | B7: Mini Laptop Go | C7: Computadoras | D7: =SUMIF(Compras!$B:$B,A7,Compras!$D:$D) -> 10 | E7: =SUMIF(Ventas!$B:$B,A7,Ventas!$D:$D) -> 4 | F7: =D7-E7 -> 6 | G7: =IF(F7<=0,"Sin Stock",IF(F7<5,"Crítico",IF(F7<10,"Stock Bajo","OK"))) -> Stock Bajo
A8: P005 | B8: Laptop Studio | C8: Computadoras | D8: =SUMIF(Compras!$B:$B,A8,Compras!$D:$D) -> 5 | E8: =SUMIF(Ventas!$B:$B,A8,Ventas!$D:$D) -> 2 | F8: =D8-E8 -> 3 | G8: =IF(F8<=0,"Sin Stock",IF(F8<5,"Crítico",IF(F8<10,"Stock Bajo","OK"))) -> Crítico
A9: P006 | B9: Mouse Gamer RGB | C9: Accesorios | D9: =SUMIF(Compras!$B:$B,A9,Compras!$D:$D) -> 30 | E9: =SUMIF(Ventas!$B:$B,A9,Ventas!$D:$D) -> 6 | F9: =D9-E9 -> 24 | G9: =IF(F9<=0,"Sin Stock",IF(F9<5,"Crítico",IF(F9<10,"Stock Bajo","OK"))) -> OK
A10: P007 | B10: Mouse Wireless Pro | C10: Accesorios | D10: =SUMIF(Compras!$B:$B,A10,Compras!$D:$D) -> 25 | E10: =SUMIF(Ventas!$B:$B,A10,Ventas!$D:$D) -> 5 | F10: =D10-E10 -> 20 | G10: =IF(F10<=0,"Sin Stock",IF(F10<5,"Crítico",IF(F10<10,"Stock Bajo","OK"))) -> OK
A11: P008 | B11: Mouse Office Silent | C11: Accesorios | D11: =SUMIF(Compras!$B:$B,A11,Compras!$D:$D) -> 40 | E11: =SUMIF(Ventas!$B:$B,A11,Ventas!$D:$D) -> 7 | F11: =D11-E11 -> 33 | G11: =IF(F11<=0,"Sin Stock",IF(F11<5,"Crítico",IF(F11<10,"Stock Bajo","OK"))) -> OK
A12: P009 | B12: Mouse UltraLight | C12: Accesorios | D12: =SUMIF(Compras!$B:$B,A12,Compras!$D:$D) -> 18 | E12: =SUMIF(Ventas!$B:$B,A12,Ventas!$D:$D) -> 3 | F12: =D12-E12 -> 15 | G12: =IF(F12<=0,"Sin Stock",IF(F12<5,"Crítico",IF(F12<10,"Stock Bajo","OK"))) -> OK
A13: P010 | B13: Mouse Precision | C13: Accesorios | D13: =SUMIF(Compras!$B:$B,A13,Compras!$D:$D) -> 22 | E13: =SUMIF(Ventas!$B:$B,A13,Ventas!$D:$D) -> 4 | F13: =D13-E13 -> 18 | G13: =IF(F13<=0,"Sin Stock",IF(F13<5,"Crítico",IF(F13<10,"Stock Bajo","OK"))) -> OK
A14: P011 | B14: Teclado Mecánico Red | C14: Accesorios | D14: =SUMIF(Compras!$B:$B,A14,Compras!$D:$D) -> 14 | E14: =SUMIF(Ventas!$B:$B,A14,Ventas!$D:$D) -> 2 | F14: =D14-E14 -> 12 | G14: =IF(F14<=0,"Sin Stock",IF(F14<5,"Crítico",IF(F14<10,"Stock Bajo","OK"))) -> OK
A15: P012 | B15: Teclado Mecánico Blue | C15: Accesorios | D15: =SUMIF(Compras!$B:$B,A15,Compras!$D:$D) -> 16 | E15: =SUMIF(Ventas!$B:$B,A15,Ventas!$D:$D) -> 2 | F15: =D15-E15 -> 14 | G15: =IF(F15<=0,"Sin Stock",IF(F15<5,"Crítico",IF(F15<10,"Stock Bajo","OK"))) -> OK
... A103: P100 | B103: Procesador CoreX | C103: Componentes | D103: =SUMIF(Compras!$B:$B,A103,Compras!$D:$D) -> 9 | E103: =SUMIF(Ventas!$B:$B,A103,Ventas!$D:$D) -> 1 | F103: =D103-E103 -> 8 | G103: =IF(F103<=0,"Sin Stock",IF(F103<5,"Crítico",IF(F103<10,"Stock Bajo","OK"))) -> Stock Bajo

Sheet Rentabilidad
A1: ANÁLISIS DE RENTABILIDAD
A2: Sistema de Gestión de Andy Silverio
A3: ID Producto | B3: Producto | C3: Categoría | D3: Costo Unitario ($) | E3: Precio Venta ($) | F3: Uds. Vendidas | G3: Ingresos ($) | H3: Costo Total ($) | I3: Ganancia ($) | J3: Margen (%)
A4: P001 | B4: =IFERROR(VLOOKUP(A4,Productos!$A:$B,2,0),"") -> Laptop X1 | C4: =IFERROR(VLOOKUP(A4,Productos!$A:$C,3,0),"") -> Computadoras | D4: =IFERROR(VLOOKUP(A4,Productos!$A:$D,4,0),"") -> 620 | E4: =IFERROR(VLOOKUP(A4,Productos!$A:$E,5,0),"") -> 920 | F4: =SUMIF(Ventas!$B:$B,A4,Ventas!$D:$D) -> 3 | G4: =IFERROR(F4*E4,0) -> 2760 | H4: =IFERROR(F4*D4,0) -> 1860 | I4: =IFERROR(G4-H4,0) -> 900 | J4: =IFERROR((G4-H4)/G4,0) -> 0.32608696
A5: P002 | B5: =IFERROR(VLOOKUP(A5,Productos!$A:$B,2,0),"") -> Laptop AirLite | C5: =IFERROR(VLOOKUP(A5,Productos!$A:$C,3,0),"") -> Computadoras | D5: =IFERROR(VLOOKUP(A5,Productos!$A:$D,4,0),"") -> 540 | E5: =IFERROR(VLOOKUP(A5,Productos!$A:$E,5,0),"") -> 820 | F5: =SUMIF(Ventas!$B:$B,A5,Ventas!$D:$D) -> 2 | G5: =IFERROR(F5*E5,0) -> 1640 | H5: =IFERROR(F5*D5,0) -> 1080 | I5: =IFERROR(G5-H5,0) -> 560 | J5: =IFERROR((G5-H5)/G5,0) -> 0.34146341
A6: P003 | B6: =IFERROR(VLOOKUP(A6,Productos!$A:$B,2,0),"") -> Laptop ProMax | C6: =IFERROR(VLOOKUP(A6,Productos!$A:$C,3,0),"") -> Computadoras | D6: =IFERROR(VLOOKUP(A6,Productos!$A:$D,4,0),"") -> 780 | E6: =IFERROR(VLOOKUP(A6,Productos!$A:$E,5,0),"") -> 1150 | F6: =SUMIF(Ventas!$B:$B,A6,Ventas!$D:$D) -> 1 | G6: =IFERROR(F6*E6,0) -> 1150 | H6: =IFERROR(F6*D6,0) -> 780 | I6: =IFERROR(G6-H6,0) -> 370 | J6: =IFERROR((G6-H6)/G6,0) -> 0.32173913
A7: P004 | B7: =IFERROR(VLOOKUP(A7,Productos!$A:$B,2,0),"") -> Mini Laptop Go | C7: =IFERROR(VLOOKUP(A7,Productos!$A:$C,3,0),"") -> Computadoras | D7: =IFERROR(VLOOKUP(A7,Productos!$A:$D,4,0),"") -> 410 | E7: =IFERROR(VLOOKUP(A7,Productos!$A:$E,5,0),"") -> 640 | F7: =SUMIF(Ventas!$B:$B,A7,Ventas!$D:$D) -> 4 | G7: =IFERROR(F7*E7,0) -> 2560 | H7: =IFERROR(F7*D7,0) -> 1640 | I7: =IFERROR(G7-H7,0) -> 920 | J7: =IFERROR((G7-H7)/G7,0) -> 0.359375
A8: P005 | B8: =IFERROR(VLOOKUP(A8,Productos!$A:$B,2,0),"") -> Laptop Studio | C8: =IFERROR(VLOOKUP(A8,Productos!$A:$C,3,0),"") -> Computadoras | D8: =IFERROR(VLOOKUP(A8,Productos!$A:$D,4,0),"") -> 890 | E8: =IFERROR(VLOOKUP(A8,Productos!$A:$E,5,0),"") -> 1290 | F8: =SUMIF(Ventas!$B:$B,A8,Ventas!$D:$D) -> 2 | G8: =IFERROR(F8*E8,0) -> 2580 | H8: =IFERROR(F8*D8,0) -> 1780 | I8: =IFERROR(G8-H8,0) -> 800 | J8: =IFERROR((G8-H8)/G8,0) -> 0.31007752
A9: P006 | B9: =IFERROR(VLOOKUP(A9,Productos!$A:$B,2,0),"") -> Mouse Gamer RGB | C9: =IFERROR(VLOOKUP(A9,Productos!$A:$C,3,0),"") -> Accesorios | D9: =IFERROR(VLOOKUP(A9,Productos!$A:$D,4,0),"") -> 18 | E9: =IFERROR(VLOOKUP(A9,Productos!$A:$E,5,0),"") -> 42 | F9: =SUMIF(Ventas!$B:$B,A9,Ventas!$D:$D) -> 6 | G9: =IFERROR(F9*E9,0) -> 252 | H9: =IFERROR(F9*D9,0) -> 108 | I9: =IFERROR(G9-H9,0) -> 144 | J9: =IFERROR((G9-H9)/G9,0) -> 0.57142857
A10: P007 | B10: =IFERROR(VLOOKUP(A10,Productos!$A:$B,2,0),"") -> Mouse Wireless Pro | C10: =IFERROR(VLOOKUP(A10,Productos!$A:$C,3,0),"") -> Accesorios | D10: =IFERROR(VLOOKUP(A10,Productos!$A:$D,4,0),"") -> 22 | E10: =IFERROR(VLOOKUP(A10,Productos!$A:$E,5,0),"") -> 48 | F10: =SUMIF(Ventas!$B:$B,A10,Ventas!$D:$D) -> 5 | G10: =IFERROR(F10*E10,0) -> 240 | H10: =IFERROR(F10*D10,0) -> 110 | I10: =IFERROR(G10-H10,0) -> 130 | J10: =IFERROR((G10-H10)/G10,0) -> 0.54166667
A11: P008 | B11: =IFERROR(VLOOKUP(A11,Productos!$A:$B,2,0),"") -> Mouse Office Silent | C11: =IFERROR(VLOOKUP(A11,Productos!$A:$C,3,0),"") -> Accesorios | D11: =IFERROR(VLOOKUP(A11,Productos!$A:$D,4,0),"") -> 12 | E11: =IFERROR(VLOOKUP(A11,Productos!$A:$E,5,0),"") -> 30 | F11: =SUMIF(Ventas!$B:$B,A11,Ventas!$D:$D) -> 7 | G11: =IFERROR(F11*E11,0) -> 210 | H11: =IFERROR(F11*D11,0) -> 84 | I11: =IFERROR(G11-H11,0) -> 126 | J11: =IFERROR((G11-H11)/G11,0) -> 0.6
A12: P009 | B12: =IFERROR(VLOOKUP(A12,Productos!$A:$B,2,0),"") -> Mouse UltraLight | C12: =IFERROR(VLOOKUP(A12,Productos!$A:$C,3,0),"") -> Accesorios | D12: =IFERROR(VLOOKUP(A12,Productos!$A:$D,4,0),"") -> 25 | E12: =IFERROR(VLOOKUP(A12,Productos!$A:$E,5,0),"") -> 55 | F12: =SUMIF(Ventas!$B:$B,A12,Ventas!$D:$D) -> 3 | G12: =IFERROR(F12*E12,0) -> 165 | H12: =IFERROR(F12*D12,0) -> 75 | I12: =IFERROR(G12-H12,0) -> 90 | J12: =IFERROR((G12-H12)/G12,0) -> 0.54545455
A13: P010 | B13: =IFERROR(VLOOKUP(A13,Productos!$A:$B,2,0),"") -> Mouse Precision | C13: =IFERROR(VLOOKUP(A13,Productos!$A:$C,3,0),"") -> Accesorios | D13: =IFERROR(VLOOKUP(A13,Productos!$A:$D,4,0),"") -> 19 | E13: =IFERROR(VLOOKUP(A13,Productos!$A:$E,5,0),"") -> 40 | F13: =SUMIF(Ventas!$B:$B,A13,Ventas!$D:$D) -> 4 | G13: =IFERROR(F13*E13,0) -> 160 | H13: =IFERROR(F13*D13,0) -> 76 | I13: =IFERROR(G13-H13,0) -> 84 | J13: =IFERROR((G13-H13)/G13,0) -> 0.525
A14: P011 | B14: =IFERROR(VLOOKUP(A14,Productos!$A:$B,2,0),"") -> Teclado Mecánico Red | C14: =IFERROR(VLOOKUP(A14,Productos!$A:$C,3,0),"") -> Accesorios | D14: =IFERROR(VLOOKUP(A14,Productos!$A:$D,4,0),"") -> 45 | E14: =IFERROR(VLOOKUP(A14,Productos!$A:$E,5,0),"") -> 95 | F14: =SUMIF(Ventas!$B:$B,A14,Ventas!$D:$D) -> 2 | G14: =IFERROR(F14*E14,0) -> 190 | H14: =IFERROR(F14*D14,0) -> 90 | I14: =IFERROR(G14-H14,0) -> 100 | J14: =IFERROR((G14-H14)/G14,0) -> 0.52631579
A15: P012 | B15: =IFERROR(VLOOKUP(A15,Productos!$A:$B,2,0),"") -> Teclado Mecánico Blue | C15: =IFERROR(VLOOKUP(A15,Productos!$A:$C,3,0),"") -> Accesorios | D15: =IFERROR(VLOOKUP(A15,Productos!$A:$D,4,0),"") -> 48 | E15: =IFERROR(VLOOKUP(A15,Productos!$A:$E,5,0),"") -> 99 | F15: =SUMIF(Ventas!$B:$B,A15,Ventas!$D:$D) -> 2 | G15: =IFERROR(F15*E15,0) -> 198 | H15: =IFERROR(F15*D15,0) -> 96 | I15: =IFERROR(G15-H15,0) -> 102 | J15: =IFERROR((G15-H15)/G15,0) -> 0.51515152
... A103: P100 | B103: =IFERROR(VLOOKUP(A103,Productos!$A:$B,2,0),"") -> Procesador CoreX | C103: =IFERROR(VLOOKUP(A103,Productos!$A:$C,3,0),"") -> Componentes | D103: =IFERROR(VLOOKUP(A103,Productos!$A:$D,4,0),"") -> 210 | E103: =IFERROR(VLOOKUP(A103,Productos!$A:$E,5,0),"") -> 360 | F103: =SUMIF(Ventas!$B:$B,A103,Ventas!$D:$D) -> 1 | G103: =IFERROR(F103*E103,0) -> 360 | H103: =IFERROR(F103*D103,0) -> 210 | I103: =IFERROR(G103-H103,0) -> 150 | J103: =IFERROR((G103-H103)/G103,0) -> 0.41666667
A104: TOTALES | F104: =SUM(F4:F103) -> 254 | G104: =SUM(G4:G103) -> 32721 | H104: =SUM(H4:H103) -> 18070 | I104: =SUM(I4:I103) -> 14651 | J104: =IFERROR((G104-H104)/G104,0) -> 0.44775526

Sheet Gráficos
A1: GRÁFICOS Y KPI
A3: Sistema de Gestión de Andy Silverio
A5: DATOS PARA GRÁFICOS
A6: Producto | B6: Unidades Vendidas | C6: Ingresos ($) | D6: Ganancia ($)
A7: =IFERROR(INDEX(Rentabilidad!$B$4:$B$103,MATCH(LARGE(Rentabilidad!$F$4:$F$103,1),Rentabilidad!$F$4:$F$103,0)),"") -> Mouse Office Silent | B7: =IFERROR(LARGE(Rentabilidad!$F$4:$F$103,1),0) -> 7 | C7: =IFERROR(INDEX(Rentabilidad!$G$4:$G$103,MATCH(LARGE(Rentabilidad!$F$4:$F$103,1),Rentabilidad!$F$4:$F$103,0)),0) -> 210 | D7: =IFERROR(INDEX(Rentabilidad!$I$4:$I$103,MATCH(LARGE(Rentabilidad!$F$4:$F$103,1),Rentabilidad!$F$4:$F$103,0)),0) -> 126
A8: =IFERROR(INDEX(Rentabilidad!$B$4:$B$103,MATCH(LARGE(Rentabilidad!$F$4:$F$103,2),Rentabilidad!$F$4:$F$103,0)),"") -> Mouse Gamer RGB | B8: =IFERROR(LARGE(Rentabilidad!$F$4:$F$103,2),0) -> 6 | C8: =IFERROR(INDEX(Rentabilidad!$G$4:$G$103,MATCH(LARGE(Rentabilidad!$F$4:$F$103,2),Rentabilidad!$F$4:$F$103,0)),0) -> 252 | D8: =IFERROR(INDEX(Rentabilidad!$I$4:$I$103,MATCH(LARGE(Rentabilidad!$F$4:$F$103,2),Rentabilidad!$F$4:$F$103,0)),0) -> 144
A9: =IFERROR(INDEX(Rentabilidad!$B$4:$B$103,MATCH(LARGE(Rentabilidad!$F$4:$F$103,3),Rentabilidad!$F$4:$F$103,0)),"") -> Mouse Gamer RGB | B9: =IFERROR(LARGE(Rentabilidad!$F$4:$F$103,3),0) -> 6 | C9: =IFERROR(INDEX(Rentabilidad!$G$4:$G$103,MATCH(LARGE(Rentabilidad!$F$4:$F$103,3),Rentabilidad!$F$4:$F$103,0)),0) -> 252 | D9: =IFERROR(INDEX(Rentabilidad!$I$4:$I$103,MATCH(LARGE(Rentabilidad!$F$4:$F$103,3),Rentabilidad!$F$4:$F$103,0)),0) -> 144
A10: =IFERROR(INDEX(Rentabilidad!$B$4:$B$103,MATCH(LARGE(Rentabilidad!$F$4:$F$103,4),Rentabilidad!$F$4:$F$103,0)),"") -> Mouse Gamer RGB | B10: =IFERROR(LARGE(Rentabilidad!$F$4:$F$103,4),0) -> 6 | C10: =IFERROR(INDEX(Rentabilidad!$G$4:$G$103,MATCH(LARGE(Rentabilidad!$F$4:$F$103,4),Rentabilidad!$F$4:$F$103,0)),0) -> 252 | D10: =IFERROR(INDEX(Rentabilidad!$I$4:$I$103,MATCH(LARGE(Rentabilidad!$F$4:$F$103,4),Rentabilidad!$F$4:$F$103,0)),0) -> 144
A11: =IFERROR(INDEX(Rentabilidad!$B$4:$B$103,MATCH(LARGE(Rentabilidad!$F$4:$F$103,5),Rentabilidad!$F$4:$F$103,0)),"") -> Mouse Wireless Pro | B11: =IFERROR(LARGE(Rentabilidad!$F$4:$F$103,5),0) -> 5 | C11: =IFERROR(INDEX(Rentabilidad!$G$4:$G$103,MATCH(LARGE(Rentabilidad!$F$4:$F$103,5),Rentabilidad!$F$4:$F$103,0)),0) -> 240 | D11: =IFERROR(INDEX(Rentabilidad!$I$4:$I$103,MATCH(LARGE(Rentabilidad!$F$4:$F$103,5),Rentabilidad!$F$4:$F$103,0)),0) -> 130
A12: =IFERROR(INDEX(Rentabilidad!$B$4:$B$103,MATCH(LARGE(Rentabilidad!$F$4:$F$103,6),Rentabilidad!$F$4:$F$103,0)),"") -> Mouse Wireless Pro | B12: =IFERROR(LARGE(Rentabilidad!$F$4:$F$103,6),0) -> 5 | C12: =IFERROR(INDEX(Rentabilidad!$G$4:$G$103,MATCH(LARGE(Rentabilidad!$F$4:$F$103,6),Rentabilidad!$F$4:$F$103,0)),0) -> 240 | D12: =IFERROR(INDEX(Rentabilidad!$I$4:$I$103,MATCH(LARGE(Rentabilidad!$F$4:$F$103,6),Rentabilidad!$F$4:$F$103,0)),0) -> 130
A13: =IFERROR(INDEX(Rentabilidad!$B$4:$B$103,MATCH(LARGE(Rentabilidad!$F$4:$F$103,7),Rentabilidad!$F$4:$F$103,0)),"") -> Mouse Wireless Pro | B13: =IFERROR(LARGE(Rentabilidad!$F$4:$F$103,7),0) -> 5 | C13: =IFERROR(INDEX(Rentabilidad!$G$4:$G$103,MATCH(LARGE(Rentabilidad!$F$4:$F$103,7),Rentabilidad!$F$4:$F$103,0)),0) -> 240 | D13: =IFERROR(INDEX(Rentabilidad!$I$4:$I$103,MATCH(LARGE(Rentabilidad!$F$4:$F$103,7),Rentabilidad!$F$4:$F$103,0)),0) -> 130
A14: =IFERROR(INDEX(Rentabilidad!$B$4:$B$103,MATCH(LARGE(Rentabilidad!$F$4:$F$103,8),Rentabilidad!$F$4:$F$103,0)),"") -> Mouse Wireless Pro | B14: =IFERROR(LARGE(Rentabilidad!$F$4:$F$103,8),0) -> 5 | C14: =IFERROR(INDEX(Rentabilidad!$G$4:$G$103,MATCH(LARGE(Rentabilidad!$F$4:$F$103,8),Rentabilidad!$F$4:$F$103,0)),0) -> 240 | D14: =IFERROR(INDEX(Rentabilidad!$I$4:$I$103,MATCH(LARGE(Rentabilidad!$F$4:$F$103,8),Rentabilidad!$F$4:$F$103,0)),0) -> 130
A15: =IFERROR(INDEX(Rentabilidad!$B$4:$B$103,MATCH(LARGE(Rentabilidad!$F$4:$F$103,9),Rentabilidad!$F$4:$F$103,0)),"") -> Mouse Wireless Pro | B15: =IFERROR(LARGE(Rentabilidad!$F$4:$F$103,9),0) -> 5 | C15: =IFERROR(INDEX(Rentabilidad!$G$4:$G$103,MATCH(LARGE(Rentabilidad!$F$4:$F$103,9),Rentabilidad!$F$4:$F$103,0)),0) -> 240 | D15: =IFERROR(INDEX(Rentabilidad!$I$4:$I$103,MATCH(LARGE(Rentabilidad!$F$4:$F$103,9),Rentabilidad!$F$4:$F$103,0)),0) -> 130
A16: =IFERROR(INDEX(Rentabilidad!$B$4:$B$103,MATCH(LARGE(Rentabilidad!$F$4:$F$103,10),Rentabilidad!$F$4:$F$103,0)),"") -> Mouse Wireless Pro | B16: =IFERROR(LARGE(Rentabilidad!$F$4:$F$103,10),0) -> 5 | C16: =IFERROR(INDEX(Rentabilidad!$G$4:$G$103,MATCH(LARGE(Rentabilidad!$F$4:$F$103,10),Rentabilidad!$F$4:$F$103,0)),0) -> 240 | D16: =IFERROR(INDEX(Rentabilidad!$I$4:$I$103,MATCH(LARGE(Rentabilidad!$F$4:$F$103,10),Rentabilidad!$F$4:$F$103,0)),0) -> 130
A19: Categoría | B19: Ganancia ($)
A20: Computadoras | B20: =SUMIF(Rentabilidad!$C$4:$C$103,A20,Rentabilidad!$I$4:$I$103) -> 3550
A21: Accesorios | B21: =SUMIF(Rentabilidad!$C$4:$C$103,A21,Rentabilidad!$I$4:$I$103) -> 1506
A22: Monitores | B22: =SUMIF(Rentabilidad!$C$4:$C$103,A22,Rentabilidad!$I$4:$I$103) -> 675
A23: Tablets | B23: =SUMIF(Rentabilidad!$C$4:$C$103,A23,Rentabilidad!$I$4:$I$103) -> 650
A24: Componentes | B24: =SUMIF(Rentabilidad!$C$4:$C$103,A24,Rentabilidad!$I$4:$I$103) -> 746
A26: Mes | B26: Ventas ($) | C26: Compras ($)
A27: Enero | B27: =SUMPRODUCT((Ventas!$A$4:$A$500>=DATE(2026,1,1))*(Ventas!$A$4:$A$500<=DATE(2026,1,31))*Ventas!$F$4:$F$500) -> 17719 | C27: =SUMPRODUCT((Compras!$A$4:$A$500>=DATE(2026,1,1))*(Compras!$A$4:$A$500<=DATE(2026,1,31))*Compras!$F$4:$F$500) -> 46077
A28: Febrero | B28: =SUMPRODUCT((Ventas!$A$4:$A$500>=DATE(2026,2,1))*(Ventas!$A$4:$A$500<=DATE(2026,2,28))*Ventas!$F$4:$F$500) -> 6217 | C28: =SUMPRODUCT((Compras!$A$4:$A$500>=DATE(2026,2,1))*(Compras!$A$4:$A$500<=DATE(2026,2,28))*Compras!$F$4:$F$500) -> 20460
A29: Marzo | B29: =SUMPRODUCT((Ventas!$A$4:$A$500>=DATE(2026,3,1))*(Ventas!$A$4:$A$500<=DATE(2026,3,31))*Ventas!$F$4:$F$500) -> 8785 | C29: =SUMPRODUCT((Compras!$A$4:$A$500>=DATE(2026,3,1))*(Compras!$A$4:$A$500<=DATE(2026,3,31))*Compras!$F$4:$F$500) -> 26071
